cybret_scanner-1.0.0.dist-info/licenses/LICENSE
scanner/__init__.py
scanner/banner.py
scanner/cli.py
scanner/config.py
scanner/agents/__init__.py
scanner/agents/base.py
scanner/agents/emergence_agent.py
scanner/agents/identity_agent.py
scanner/agents/logic_agent.py
scanner/agents/orchestrator.py
scanner/agents/state_agent.py
scanner/agents/temporal_agent.py
scanner/agents/trust_agent.py
scanner/analyzers/inline_handler_analyzer.py
scanner/autonomy/__init__.py
scanner/autonomy/engine.py
scanner/autonomy/trust_scorer.py
scanner/detectors/__init__.py
scanner/detectors/auth_bypass.py
scanner/detectors/base.py
scanner/detectors/bola_2stage.py
scanner/detectors/guardrails.py
scanner/detectors/idor.py
scanner/detectors/llm_enhanced_idor.py
scanner/extractors/__init__.py
scanner/extractors/route_graph_extractor.py
scanner/extractors/symbol_table.py
scanner/graph/__init__.py
scanner/graph/builder.py
scanner/graph/queries.py
scanner/intent/__init__.py
scanner/intent/graph_schema.py
scanner/intent/inference_engine.py
scanner/llm/__init__.py
scanner/llm/agents.py
scanner/llm/context_builder.py
scanner/llm/enhanced_intent_analyzer.py
scanner/llm/llm_client.py
scanner/llm/openrouter_client.py
scanner/llm/remediation.py
scanner/llm/smart_detector.py
scanner/models/__init__.py
scanner/models/route_graph.py
scanner/parsers/__init__.py
scanner/parsers/base.py
scanner/parsers/go_parser.py
scanner/parsers/java_parser.py
scanner/parsers/javascript_parser.py
scanner/parsers/python_parser.py
scanner/simulation/__init__.py
scanner/simulation/exploit_replay.py
scanner/utils/__init__.py
scanner/utils/fix_applier.py
scanner/utils/pr_creator.py
scanner/utils/test_generator.py
cybret_scanner-1.0.0.dist-info/METADATA
cybret_scanner-1.0.0.dist-info/WHEEL
cybret_scanner-1.0.0.dist-info/entry_points.txt
cybret_scanner-1.0.0.dist-info/top_level.txt
cybret_scanner-1.0.0.dist-info/RECORD
