Metadata-Version: 2.4
Name: cybret-scanner
Version: 1.0.0
Summary: AI-Powered Logic Vulnerability Scanner with Autonomous Remediation
Author-email: CYBRET AI <contact@cybret.ai>
Maintainer-email: CYBRET AI <contact@cybret.ai>
License: MIT
Project-URL: Homepage, https://github.com/cybret/cybret-scanner
Project-URL: Documentation, https://github.com/cybret/cybret-scanner#readme
Project-URL: Repository, https://github.com/cybret/cybret-scanner
Project-URL: Issues, https://github.com/cybret/cybret-scanner/issues
Project-URL: Changelog, https://github.com/cybret/cybret-scanner/releases
Keywords: security,vulnerability-scanner,static-analysis,sast,idor,bola,logic-vulnerabilities,ai-security,llm,autonomous-remediation,devsecops
Classifier: Development Status :: 4 - Beta
Classifier: Intended Audience :: Developers
Classifier: Intended Audience :: Information Technology
Classifier: Topic :: Security
Classifier: Topic :: Software Development :: Quality Assurance
Classifier: Topic :: Software Development :: Testing
Classifier: License :: OSI Approved :: MIT License
Classifier: Programming Language :: Python :: 3
Classifier: Programming Language :: Python :: 3.9
Classifier: Programming Language :: Python :: 3.10
Classifier: Programming Language :: Python :: 3.11
Classifier: Programming Language :: Python :: 3.12
Classifier: Operating System :: OS Independent
Classifier: Environment :: Console
Classifier: Typing :: Typed
Requires-Python: >=3.9
License-File: LICENSE
Requires-Dist: fastapi>=0.109.0
Requires-Dist: uvicorn[standard]>=0.27.0
Requires-Dist: pydantic>=2.5.3
Requires-Dist: pydantic-settings>=2.1.0
Requires-Dist: neo4j>=5.16.0
Requires-Dist: ast-comments>=1.2.2
Requires-Dist: astor>=0.8.1
Requires-Dist: esprima>=4.0.1
Requires-Dist: javalang>=0.13.0
Requires-Dist: httpx>=0.26.0
Requires-Dist: aiohttp>=3.9.1
Requires-Dist: click>=8.1.7
Requires-Dist: rich>=13.7.0
Requires-Dist: typer>=0.9.0
Requires-Dist: gitpython>=3.1.40
Requires-Dist: jsonschema>=4.20.0
Requires-Dist: structlog>=24.1.0
Requires-Dist: python-json-logger>=2.0.7
Requires-Dist: python-jose[cryptography]>=3.3.0
Requires-Dist: passlib[bcrypt]>=1.7.4
Requires-Dist: python-dotenv>=1.0.0
Requires-Dist: pyyaml>=6.0.1
Requires-Dist: prometheus-client>=0.19.0
Requires-Dist: slowapi>=0.1.9
Requires-Dist: python-multipart>=0.0.6
Requires-Dist: celery>=5.3.6
Requires-Dist: redis>=5.0.1
Requires-Dist: orjson>=3.9.12
Requires-Dist: python-magic>=0.4.27
Requires-Dist: tqdm>=4.66.1
Requires-Dist: tenacity>=8.2.3
Provides-Extra: llm
Requires-Dist: openai>=1.12.0; extra == "llm"
Requires-Dist: anthropic>=0.18.0; extra == "llm"
Requires-Dist: langchain>=0.1.6; extra == "llm"
Requires-Dist: langchain-openai>=0.0.5; extra == "llm"
Requires-Dist: langchain-anthropic>=0.1.1; extra == "llm"
Requires-Dist: langgraph>=0.0.20; extra == "llm"
Requires-Dist: tiktoken>=0.6.0; extra == "llm"
Provides-Extra: dev
Requires-Dist: pytest>=7.4.4; extra == "dev"
Requires-Dist: pytest-cov>=4.1.0; extra == "dev"
Requires-Dist: pytest-asyncio>=0.23.3; extra == "dev"
Requires-Dist: pytest-mock>=3.12.0; extra == "dev"
Requires-Dist: black>=23.12.1; extra == "dev"
Requires-Dist: flake8>=7.0.0; extra == "dev"
Requires-Dist: mypy>=1.8.0; extra == "dev"
Requires-Dist: isort>=5.13.2; extra == "dev"
Requires-Dist: types-PyYAML>=6.0.12.12; extra == "dev"
Requires-Dist: types-redis>=4.6.0.11; extra == "dev"
Requires-Dist: types-requests>=2.31.0.20240106; extra == "dev"
Provides-Extra: all
Requires-Dist: cybret-scanner[dev,llm]; extra == "all"
Dynamic: license-file
